{
  "log12-7-2022": [
    {
      "id": "l5i8alwrg92eqql6cye",
      "Status": "folder was not changed",
      "TimePushed": "7/12/2022, 4:48:00 PM"
    },
    {
      "id": "l5i8c24yyidx4dek6cf",
      "Status": "git update complete",
      "TimePushed": "7/12/2022, 4:49:08 PM"
    },
    {
      "id": "l5i8daaobqslfejcpsp",
      "Status": "git update complete",
      "TimePushed": "7/12/2022, 4:50:05 PM"
    },
    {
      "id": "l5i8ejq8407p7s32ji3",
      "Status": "git update complete",
      "TimePushed": "7/12/2022, 4:51:04 PM"
    },
    {
      "id": "l5i8ftuh4ykch0z3fca",
      "Status": "git update complete",
      "TimePushed": "7/12/2022, 4:52:04 PM"
    },
    {
      "id": "l5i8h4uf85x08x4q9t9",
      "Status": "git update complete",
      "TimePushed": "7/12/2022, 4:53:05 PM"
    },
    {
      "id": "l5i8iewodxwtm540557",
      "Status": "git update complete",
      "TimePushed": "7/12/2022, 4:54:04 PM"
    },
    {
      "id": "l5i8jp470eb4b1c3aelp",
      "Status": "git update complete",
      "TimePushed": "7/12/2022, 4:55:04 PM"
    },
    {
      "id": "l5i8kzwvym1jlhiqvqe",
      "Status": "git update complete",
      "TimePushed": "7/12/2022, 4:56:05 PM"
    },
    {
      "id": "l5i8mb0uusmuhcs1u0l",
      "Status": "git update complete",
      "TimePushed": "7/12/2022, 4:57:06 PM"
    },
    {
      "id": "l5i8p32tj6win39s11",
      "Status": "git update complete",
      "TimePushed": "7/12/2022, 4:59:16 PM"
    },
    {
      "id": "l5i8qffpst9o9b1pyzb",
      "Status": "git update complete",
      "TimePushed": "7/12/2022, 5:00:18 PM"
    },
    {
      "id": "l5i8rfsbvv0ucp8ci69",
      "Status": "git update complete",
      "TimePushed": "7/12/2022, 5:01:05 PM"
    },
    {
      "id": "l5i8sp7lzs39lgszid",
      "Status": "git update complete",
      "TimePushed": "7/12/2022, 5:02:04 PM"
    },
    {
      "id": "l5i8tzwsq8koj8421c",
      "Status": "git update complete",
      "TimePushed": "7/12/2022, 5:03:05 PM"
    },
    {
      "id": "l5i8vb9r6tlvt60v3wu",
      "Status": "git update complete",
      "TimePushed": "7/12/2022, 5:04:06 PM"
    },
    {
      "id": "l5i8wk2j4nhpjhmv7ib",
      "Status": "git update complete",
      "TimePushed": "7/12/2022, 5:05:04 PM"
    },
    {
      "id": "l5i8xu5ggtiurqhencu",
      "Status": "git update complete",
      "TimePushed": "7/12/2022, 5:06:04 PM"
    },
    {
      "id": "l5i8z4opc4b2tco114u",
      "Status": "git update complete",
      "TimePushed": "7/12/2022, 5:07:04 PM"
    },
    {
      "id": "l5i90f2b98ql5z2hhp5",
      "Status": "git update complete",
      "TimePushed": "7/12/2022, 5:08:04 PM"
    },
    {
      "id": "l5i91pjzvee52a062ti",
      "Status": "git update complete",
      "TimePushed": "7/12/2022, 5:09:05 PM"
    },
    {
      "id": "l5i9306v1tdalqrq0ya",
      "Status": "git update complete",
      "TimePushed": "7/12/2022, 5:10:05 PM"
    },
    {
      "id": "l5i949v6a37m7zhho5d",
      "Status": "git update complete",
      "TimePushed": "7/12/2022, 5:11:04 PM"
    },
    {
      "id": "l5i95kjxy98j5uyadx",
      "Status": "git update complete",
      "TimePushed": "7/12/2022, 5:12:05 PM"
    },
    {
      "id": "l5i96x8y5nqnv40hgc",
      "Status": "git update complete",
      "TimePushed": "7/12/2022, 5:13:08 PM"
    },
    {
      "id": "l5i985xqfj35bprvhqm",
      "Status": "git update complete",
      "TimePushed": "7/12/2022, 5:14:06 PM"
    },
    {
      "id": "l5i99gf40ogx0oignxlg",
      "Status": "git update complete",
      "TimePushed": "7/12/2022, 5:15:06 PM"
    },
    {
      "id": "l5i9apndtcqt8c052io",
      "Status": "git update complete",
      "TimePushed": "7/12/2022, 5:16:05 PM"
    },
    {
      "id": "l5i9c0nu2j48hfm28hl",
      "Status": "git update complete",
      "TimePushed": "7/12/2022, 5:17:06 PM"
    },
    {
      "id": "l5i9daa0s4v5v4opt3j",
      "Status": "git update complete",
      "TimePushed": "7/12/2022, 5:18:05 PM"
    },
    {
      "id": "l5i9el059xrzenfddo8",
      "Status": "git update complete",
      "TimePushed": "7/12/2022, 5:19:05 PM"
    },
    {
      "id": "l5i9fv50x4le2peev9d",
      "Status": "git update complete",
      "TimePushed": "7/12/2022, 5:20:05 PM"
    },
    {
      "id": "l5i9h59dk1pfaai45m",
      "Status": "git update complete",
      "TimePushed": "7/12/2022, 5:21:05 PM"
    },
    {
      "id": "l5i9igwhzf6w25xa7qs",
      "Status": "git update complete",
      "TimePushed": "7/12/2022, 5:22:07 PM"
    },
    {
      "id": "l5i9jqrey1dnyb516nj",
      "Status": "git update complete",
      "TimePushed": "7/12/2022, 5:23:06 PM"
    },
    {
      "id": "l5i9kz6yp3dnixrwb6",
      "Status": "git update complete",
      "TimePushed": "7/12/2022, 5:24:04 PM"
    }
  ],
  "log13-7-2022": [
    {
      "id": "l5j3rpiwlwsqtbp63ec",
      "Status": "git update complete",
      "TimePushed": "7/13/2022, 7:29:06 AM"
    },
    {
      "id": "l5j3sxz2rfwebvj8h",
      "Status": "git update complete",
      "TimePushed": "7/13/2022, 7:30:04 AM"
    },
    {
      "id": "l5j3u8hmziqvbqthcdf",
      "Status": "git update complete",
      "TimePushed": "7/13/2022, 7:31:04 AM"
    },
    {
      "id": "l5j3vjmwetqa84fg48k",
      "Status": "git update complete",
      "TimePushed": "7/13/2022, 7:32:05 AM"
    },
    {
      "id": "l5j3wt143sshp44vco3",
      "Status": "git update complete",
      "TimePushed": "7/13/2022, 7:33:04 AM"
    },
    {
      "id": "l5j3zdrldrqlzxwp2mw",
      "Status": "git update complete",
      "TimePushed": "7/13/2022, 7:35:04 AM"
    },
    {
      "id": "l5j40nmn31tabnm6l9c",
      "Status": "git update complete",
      "TimePushed": "7/13/2022, 7:36:04 AM"
    },
    {
      "id": "l5j420ig3dwu1gp8sw",
      "Status": "git update complete",
      "TimePushed": "7/13/2022, 7:37:07 AM"
    },
    {
      "id": "l5j4390ju7j47qpqp6g",
      "Status": "git update complete",
      "TimePushed": "7/13/2022, 7:38:05 AM"
    },
    {
      "id": "l5j44j2x83kxjyupnfn",
      "Status": "git update complete",
      "TimePushed": "7/13/2022, 7:39:04 AM"
    },
    {
      "id": "l5j45svh0grblbyb9ajn",
      "Status": "git update complete",
      "TimePushed": "7/13/2022, 7:40:04 AM"
    },
    {
      "id": "l5j473dvaxz1za2ygl",
      "Status": "git update complete",
      "TimePushed": "7/13/2022, 7:41:04 AM"
    },
    {
      "id": "l5j49oh1ub01mx0kaba",
      "Status": "git update complete",
      "TimePushed": "7/13/2022, 7:43:05 AM"
    },
    {
      "id": "l5j4aylmgglugc6nhfw",
      "Status": "git update complete",
      "TimePushed": "7/13/2022, 7:44:04 AM"
    },
    {
      "id": "l5j4c8oitretpcvvxsm",
      "Status": "git update complete",
      "TimePushed": "7/13/2022, 7:45:04 AM"
    },
    {
      "id": "l5j4diq6dwa497yrexf",
      "Status": "git update complete",
      "TimePushed": "7/13/2022, 7:46:04 AM"
    },
    {
      "id": "l5j4ett722n5yfq5ld6",
      "Status": "git update complete",
      "TimePushed": "7/13/2022, 7:47:05 AM"
    },
    {
      "id": "l5j4g3r1waau56buezs",
      "Status": "git update complete",
      "TimePushed": "7/13/2022, 7:48:04 AM"
    },
    {
      "id": "l5j4hdxrh8d6rcv01i6",
      "Status": "git update complete",
      "TimePushed": "7/13/2022, 7:49:04 AM"
    },
    {
      "id": "l5j4inyjv142comw2x",
      "Status": "git update complete",
      "TimePushed": "7/13/2022, 7:50:04 AM"
    },
    {
      "id": "l5j4jyonsb77xaipfa",
      "Status": "git update complete",
      "TimePushed": "7/13/2022, 7:51:04 AM"
    },
    {
      "id": "l5j4l8tj5i6ves3mafi",
      "Status": "git update complete",
      "TimePushed": "7/13/2022, 7:52:04 AM"
    },
    {
      "id": "l5j4mitckybhqlknhwh",
      "Status": "git update complete",
      "TimePushed": "7/13/2022, 7:53:04 AM"
    },
    {
      "id": "l5j4ntbtphd493g0kj",
      "Status": "git update complete",
      "TimePushed": "7/13/2022, 7:54:04 AM"
    },
    {
      "id": "l5j4p3z9f0q7cd37tge",
      "Status": "git update complete",
      "TimePushed": "7/13/2022, 7:55:05 AM"
    },
    {
      "id": "l5j4qdrpsl2b39igq6",
      "Status": "git update complete",
      "TimePushed": "7/13/2022, 7:56:04 AM"
    },
    {
      "id": "l5j4rochw1sn3eqxef9",
      "Status": "git update complete",
      "TimePushed": "7/13/2022, 7:57:04 AM"
    },
    {
      "id": "l5j4sy4nazh4ga4z3zv",
      "Status": "git update complete",
      "TimePushed": "7/13/2022, 7:58:04 AM"
    },
    {
      "id": "l5j4u8ricbq3ub4q3pp",
      "Status": "git update complete",
      "TimePushed": "7/13/2022, 7:59:04 AM"
    },
    {
      "id": "l5j4vkkmio285liib6m",
      "Status": "git update complete",
      "TimePushed": "7/13/2022, 8:00:06 AM"
    },
    {
      "id": "l5j4x52tini5audahui",
      "Status": "git update complete",
      "TimePushed": "7/13/2022, 8:01:19 AM"
    },
    {
      "id": "l5j4y4bu92mln8k7p3",
      "Status": "git update complete",
      "TimePushed": "7/13/2022, 8:02:05 AM"
    },
    {
      "id": "l5j4zebuaz1r3e5njs6",
      "Status": "git update complete",
      "TimePushed": "7/13/2022, 8:03:05 AM"
    },
    {
      "id": "l5j50obd76yxyfvxqq9",
      "Status": "git update complete",
      "TimePushed": "7/13/2022, 8:04:04 AM"
    },
    {
      "id": "l5j51yy6l0ngclhlhve",
      "Status": "git update complete",
      "TimePushed": "7/13/2022, 8:05:05 AM"
    },
    {
      "id": "l5j539he3yy0tnchpkm",
      "Status": "git update complete",
      "TimePushed": "7/13/2022, 8:06:05 AM"
    },
    {
      "id": "l5j54kg4pyi6a0uasf",
      "Status": "git update complete",
      "TimePushed": "7/13/2022, 8:07:06 AM"
    },
    {
      "id": "l5j55vhk8iq4x081ygm",
      "Status": "git update complete",
      "TimePushed": "7/13/2022, 8:08:07 AM"
    },
    {
      "id": "l5j574f6daac0ykp1cd",
      "Status": "git update complete",
      "TimePushed": "7/13/2022, 8:09:05 AM"
    },
    {
      "id": "l5j58evyhrmtxn7ti9e",
      "Status": "git update complete",
      "TimePushed": "7/13/2022, 8:10:05 AM"
    },
    {
      "id": "l5j59p07h4slrjwktfa",
      "Status": "git update complete",
      "TimePushed": "7/13/2022, 8:11:05 AM"
    },
    {
      "id": "l5j5az211i5o5rkor03",
      "Status": "git update complete",
      "TimePushed": "7/13/2022, 8:12:05 AM"
    },
    {
      "id": "l5j5c91y4jvhfhtxvkp",
      "Status": "git update complete",
      "TimePushed": "7/13/2022, 8:13:04 AM"
    },
    {
      "id": "l5j5dib35g7efex2hrt",
      "Status": "git update complete",
      "TimePushed": "7/13/2022, 8:14:03 AM"
    },
    {
      "id": "l5j5etez8rvd9jzzrfg",
      "Status": "git update complete",
      "TimePushed": "7/13/2022, 8:15:04 AM"
    },
    {
      "id": "l5j5g3tkohwtroapl4m",
      "Status": "git update complete",
      "TimePushed": "7/13/2022, 8:16:04 AM"
    },
    {
      "id": "l5j5hd4wawh09m8vez6",
      "Status": "git update complete",
      "TimePushed": "7/13/2022, 8:17:03 AM"
    },
    {
      "id": "l5j5ioj5l7jwdkg9qai",
      "Status": "git update complete",
      "TimePushed": "7/13/2022, 8:18:04 AM"
    },
    {
      "id": "l5j5jyddbdaw7uv8n8",
      "Status": "git update complete",
      "TimePushed": "7/13/2022, 8:19:04 AM"
    },
    {
      "id": "l5j5l9p6gw4y2qdycqm",
      "Status": "git update complete",
      "TimePushed": "7/13/2022, 8:20:05 AM"
    },
    {
      "id": "l5j5mjgocmqjtuv5fuw",
      "Status": "git update complete",
      "TimePushed": "7/13/2022, 8:21:04 AM"
    },
    {
      "id": "l5j5nt9yg8qzne6hcuo",
      "Status": "git update complete",
      "TimePushed": "7/13/2022, 8:22:04 AM"
    },
    {
      "id": "l5j5p3s26nxishd7pdc",
      "Status": "git update complete",
      "TimePushed": "7/13/2022, 8:23:04 AM"
    },
    {
      "id": "l5j5qdg35c1zgq95ipq",
      "Status": "git update complete",
      "TimePushed": "7/13/2022, 8:24:03 AM"
    },
    {
      "id": "l5j5ro9wjgi080bcj7l",
      "Status": "git update complete",
      "TimePushed": "7/13/2022, 8:25:04 AM"
    },
    {
      "id": "l5j5sywzl6llrrdmolf",
      "Status": "git update complete",
      "TimePushed": "7/13/2022, 8:26:04 AM"
    },
    {
      "id": "l5j5u95hxllts2al2j",
      "Status": "git update complete",
      "TimePushed": "7/13/2022, 8:27:04 AM"
    },
    {
      "id": "l5j5vjemhjgq58whnto",
      "Status": "git update complete",
      "TimePushed": "7/13/2022, 8:28:04 AM"
    },
    {
      "id": "l5j5wvckl1vwgznc83",
      "Status": "git update complete",
      "TimePushed": "7/13/2022, 8:29:06 AM"
    },
    {
      "id": "l5j5y49x07647fjjgauk",
      "Status": "git update complete",
      "TimePushed": "7/13/2022, 8:30:04 AM"
    },
    {
      "id": "l5j5zemzcwocatkcrtb",
      "Status": "git update complete",
      "TimePushed": "7/13/2022, 8:31:05 AM"
    },
    {
      "id": "l5j60p6ryhxnqph1uqt",
      "Status": "git update complete",
      "TimePushed": "7/13/2022, 8:32:05 AM"
    },
    {
      "id": "l5j61yruybslgzwuecc",
      "Status": "git update complete",
      "TimePushed": "7/13/2022, 8:33:04 AM"
    },
    {
      "id": "l5j639a9klw77avjdki",
      "Status": "git update complete",
      "TimePushed": "7/13/2022, 8:34:04 AM"
    },
    {
      "id": "l5j64jpreyx3q3rle15",
      "Status": "git update complete",
      "TimePushed": "7/13/2022, 8:35:04 AM"
    },
    {
      "id": "l5j65u6ov0vz1n3ogel",
      "Status": "git update complete",
      "TimePushed": "7/13/2022, 8:36:05 AM"
    },
    {
      "id": "l5j674mbw9uzi460nd",
      "Status": "git update complete",
      "TimePushed": "7/13/2022, 8:37:05 AM"
    },
    {
      "id": "l5j68ely1yry59r0q2c",
      "Status": "git update complete",
      "TimePushed": "7/13/2022, 8:38:04 AM"
    },
    {
      "id": "l5j69orzb61hwaoucl9",
      "Status": "git update complete",
      "TimePushed": "7/13/2022, 8:39:04 AM"
    },
    {
      "id": "l5j6azsivx4p4ctwxe8",
      "Status": "git update complete",
      "TimePushed": "7/13/2022, 8:40:05 AM"
    },
    {
      "id": "l5j6c99q9ne8j3yka6",
      "Status": "git update complete",
      "TimePushed": "7/13/2022, 8:41:04 AM"
    },
    {
      "id": "l5j6djq0ll30p63xx7d",
      "Status": "git update complete",
      "TimePushed": "7/13/2022, 8:42:04 AM"
    },
    {
      "id": "l5j6eu0fmty9rxb6vd",
      "Status": "git update complete",
      "TimePushed": "7/13/2022, 8:43:04 AM"
    }
  ],
  "log14-7-2022": [
    {
      "id": "l5kww2pacpmlwn1549a",
      "Status": "git update complete",
      "TimePushed": "7/14/2022, 1:52:05 PM"
    },
    {
      "id": "l5kwxc9cjffbv7mb7s",
      "Status": "git update complete",
      "TimePushed": "7/14/2022, 1:53:04 PM"
    },
    {
      "id": "l5kwyn6dhw2rwaj6bqj",
      "Status": "git update complete",
      "TimePushed": "7/14/2022, 1:54:05 PM"
    },
    {
      "id": "l5kwzxm08vo5esm9trd",
      "Status": "git update complete",
      "TimePushed": "7/14/2022, 1:55:05 PM"
    },
    {
      "id": "l5kx1833qfw73eqhujt",
      "Status": "git update complete",
      "TimePushed": "7/14/2022, 1:56:05 PM"
    },
    {
      "id": "l5kx2hmvjjt72kihsis",
      "Status": "git update complete",
      "TimePushed": "7/14/2022, 1:57:04 PM"
    },
    {
      "id": "l5kx3s22rqzwq7vsh7h",
      "Status": "git update complete",
      "TimePushed": "7/14/2022, 1:58:04 PM"
    },
    {
      "id": "l5kx528j86vj7om5a0m",
      "Status": "git update complete",
      "TimePushed": "7/14/2022, 1:59:04 PM"
    },
    {
      "id": "l5kx6d7exseon9smxte",
      "Status": "git update complete",
      "TimePushed": "7/14/2022, 2:00:05 PM"
    },
    {
      "id": "l5kx7nmet14zx7jsaj",
      "Status": "git update complete",
      "TimePushed": "7/14/2022, 2:01:05 PM"
    },
    {
      "id": "l5kx8x6h2jrdby8ouxp",
      "Status": "git update complete",
      "TimePushed": "7/14/2022, 2:02:04 PM"
    },
    {
      "id": "l5kxa7i3hych3tccmho",
      "Status": "git update complete",
      "TimePushed": "7/14/2022, 2:03:04 PM"
    },
    {
      "id": "l5kxbk4cgncvwb9nyc",
      "Status": "git update complete",
      "TimePushed": "7/14/2022, 2:04:07 PM"
    },
    {
      "id": "l5kxcthspfn0b5q20wn",
      "Status": "git update complete",
      "TimePushed": "7/14/2022, 2:05:06 PM"
    },
    {
      "id": "l5kxe303afj9eyrcc4e",
      "Status": "git update complete",
      "TimePushed": "7/14/2022, 2:06:05 PM"
    },
    {
      "id": "l5kxfct3u82i5jj6r6s",
      "Status": "git update complete",
      "TimePushed": "7/14/2022, 2:07:04 PM"
    },
    {
      "id": "l5kxgontc98mrv21cu8",
      "Status": "git update complete",
      "TimePushed": "7/14/2022, 2:08:07 PM"
    },
    {
      "id": "l5kxhzo1493y7yr5ph9",
      "Status": "git update complete",
      "TimePushed": "7/14/2022, 2:09:07 PM"
    },
    {
      "id": "l5kxj86emo05c8tqjk",
      "Status": "git update complete",
      "TimePushed": "7/14/2022, 2:10:05 PM"
    },
    {
      "id": "l5kxki6g4ik1dj90zrt",
      "Status": "git update complete",
      "TimePushed": "7/14/2022, 2:11:05 PM"
    },
    {
      "id": "l5kxlsysa0nemyebs4k",
      "Status": "git update complete",
      "TimePushed": "7/14/2022, 2:12:05 PM"
    },
    {
      "id": "l5kxn5eebdaq66bf9t",
      "Status": "git update complete",
      "TimePushed": "7/14/2022, 2:13:08 PM"
    },
    {
      "id": "l5kxofvvbiee0adtbq6",
      "Status": "git update complete",
      "TimePushed": "7/14/2022, 2:14:08 PM"
    },
    {
      "id": "l5kxpou22xmkhxu5wra",
      "Status": "git update complete",
      "TimePushed": "7/14/2022, 2:15:07 PM"
    },
    {
      "id": "l5kxr2sgginiat0dvc5",
      "Status": "git update complete",
      "TimePushed": "7/14/2022, 2:16:11 PM"
    },
    {
      "id": "l5kxsb3tn7jb32284k",
      "Status": "git update complete",
      "TimePushed": "7/14/2022, 2:17:09 PM"
    },
    {
      "id": "l5kxtifjtjmn2wnwei",
      "Status": "git update complete",
      "TimePushed": "7/14/2022, 2:18:05 PM"
    },
    {
      "id": "l5kxus5x5rx8wka5xmt",
      "Status": "git update complete",
      "TimePushed": "7/14/2022, 2:19:04 PM"
    },
    {
      "id": "l5kxw6asyfjzhg0pxe",
      "Status": "git update complete",
      "TimePushed": "7/14/2022, 2:20:09 PM"
    },
    {
      "id": "l5kxxevk6zofx3oxvh9",
      "Status": "git update complete",
      "TimePushed": "7/14/2022, 2:21:07 PM"
    },
    {
      "id": "l5kxyr558fq444ifotw",
      "Status": "git update complete",
      "TimePushed": "7/14/2022, 2:22:10 PM"
    },
    {
      "id": "l5kxzyl6vmpb5mw55cd",
      "Status": "git update complete",
      "TimePushed": "7/14/2022, 2:23:06 PM"
    },
    {
      "id": "l5ky19nkqox58hec52s",
      "Status": "git update complete",
      "TimePushed": "7/14/2022, 2:24:07 PM"
    },
    {
      "id": "l5ky2idchiahn89xbb",
      "Status": "git update complete",
      "TimePushed": "7/14/2022, 2:25:05 PM"
    },
    {
      "id": "l5ky3sc8cj9a8j0top",
      "Status": "git update complete",
      "TimePushed": "7/14/2022, 2:26:04 PM"
    },
    {
      "id": "l5ky52ck51ew7e4y3ap",
      "Status": "git update complete",
      "TimePushed": "7/14/2022, 2:27:04 PM"
    },
    {
      "id": "l5ky6d3pgptr4dzxlqq",
      "Status": "git update complete",
      "TimePushed": "7/14/2022, 2:28:05 PM"
    },
    {
      "id": "l5ky7n4k1cfc65qf7ahi",
      "Status": "git update complete",
      "TimePushed": "7/14/2022, 2:29:04 PM"
    },
    {
      "id": "l5ky8xmr0peqgoeem3vl",
      "Status": "git update complete",
      "TimePushed": "7/14/2022, 2:30:04 PM"
    },
    {
      "id": "l5kya850sifyb7p5s1k",
      "Status": "git update complete",
      "TimePushed": "7/14/2022, 2:31:05 PM"
    },
    {
      "id": "l5kybi9qzg3jnzfj44",
      "Status": "git update complete",
      "TimePushed": "7/14/2022, 2:32:05 PM"
    },
    {
      "id": "l5kyct0qb3as1ugxjld",
      "Status": "git update complete",
      "TimePushed": "7/14/2022, 2:33:05 PM"
    },
    {
      "id": "l5kye2i1fohdibqmhp6",
      "Status": "git update complete",
      "TimePushed": "7/14/2022, 2:34:04 PM"
    },
    {
      "id": "l5kyfd5sdwydtypyx0m",
      "Status": "git update complete",
      "TimePushed": "7/14/2022, 2:35:05 PM"
    },
    {
      "id": "l5kygn4s3v7fato0qhj",
      "Status": "git update complete",
      "TimePushed": "7/14/2022, 2:36:04 PM"
    },
    {
      "id": "l5kyhy63f9ruk8iyokc",
      "Status": "git update complete",
      "TimePushed": "7/14/2022, 2:37:05 PM"
    },
    {
      "id": "l5kyjb08v7mq3o6egq",
      "Status": "git update complete",
      "TimePushed": "7/14/2022, 2:38:08 PM"
    },
    {
      "id": "l5kykpm6nwdreu537q",
      "Status": "git update complete",
      "TimePushed": "7/14/2022, 2:39:14 PM"
    },
    {
      "id": "l5kylusp1dcln6kv9q9",
      "Status": "git update complete",
      "TimePushed": "7/14/2022, 2:40:07 PM"
    },
    {
      "id": "l5kyn3gqdlg3gbk4k1i",
      "Status": "git update complete",
      "TimePushed": "7/14/2022, 2:41:05 PM"
    },
    {
      "id": "l5kyoddvqt33xw8prnf",
      "Status": "git update complete",
      "TimePushed": "7/14/2022, 2:42:05 PM"
    },
    {
      "id": "l5kypplp6h2v1ovdoxi",
      "Status": "git update complete",
      "TimePushed": "7/14/2022, 2:43:07 PM"
    },
    {
      "id": "l5kyqzqqauw4avsku8",
      "Status": "git update complete",
      "TimePushed": "7/14/2022, 2:44:07 PM"
    },
    {
      "id": "l5kysbr8unh2xubgfvo",
      "Status": "git update complete",
      "TimePushed": "7/14/2022, 2:45:09 PM"
    },
    {
      "id": "l5kytjqnfgl8qfe2kq9",
      "Status": "git update complete",
      "TimePushed": "7/14/2022, 2:46:06 PM"
    },
    {
      "id": "l5kyut7uc58yoi3yov",
      "Status": "git update complete",
      "TimePushed": "7/14/2022, 2:47:05 PM"
    },
    {
      "id": "l5kyw3ke6ponfkci55b",
      "Status": "git update complete",
      "TimePushed": "7/14/2022, 2:48:05 PM"
    },
    {
      "id": "l5kyxei2nc7b36m2xv",
      "Status": "git update complete",
      "TimePushed": "7/14/2022, 2:49:06 PM"
    },
    {
      "id": "l5kyyn55ff34nze9ycl",
      "Status": "git update complete",
      "TimePushed": "7/14/2022, 2:50:04 PM"
    },
    {
      "id": "l5kyzzjjs58xr9sznr8",
      "Status": "git update complete",
      "TimePushed": "7/14/2022, 2:51:07 PM"
    },
    {
      "id": "l5kz19ythys9o8uth7",
      "Status": "git update complete",
      "TimePushed": "7/14/2022, 2:52:07 PM"
    },
    {
      "id": "l5kz2in61biy5xqo7ash",
      "Status": "git update complete",
      "TimePushed": "7/14/2022, 2:53:05 PM"
    },
    {
      "id": "l5kz3t0k16f5wsqsfz7",
      "Status": "git update complete",
      "TimePushed": "7/14/2022, 2:54:05 PM"
    },
    {
      "id": "l5kz54k8dkt868jemf6",
      "Status": "git update complete",
      "TimePushed": "7/14/2022, 2:55:06 PM"
    },
    {
      "id": "l5kz6duzbyos85rrbyp",
      "Status": "git update complete",
      "TimePushed": "7/14/2022, 2:56:05 PM"
    },
    {
      "id": "l5kz7o484ejxuig0kgp",
      "Status": "git update complete",
      "TimePushed": "7/14/2022, 2:57:05 PM"
    },
    {
      "id": "l5kz8yax5hx2yg9fedl",
      "Status": "git update complete",
      "TimePushed": "7/14/2022, 2:58:05 PM"
    },
    {
      "id": "l5kza8mjapfknzvtux9",
      "Status": "git update complete",
      "TimePushed": "7/14/2022, 2:59:05 PM"
    },
    {
      "id": "l5kzbjtqgchdjyk1smf",
      "Status": "git update complete",
      "TimePushed": "7/14/2022, 3:00:06 PM"
    },
    {
      "id": "l5kzctlugjeiyt0oim",
      "Status": "git update complete",
      "TimePushed": "7/14/2022, 3:01:06 PM"
    },
    {
      "id": "l5kze3il5ztarnpq4b",
      "Status": "git update complete",
      "TimePushed": "7/14/2022, 3:02:05 PM"
    },
    {
      "id": "l5kzfdx7aomk6m20r3m",
      "Status": "git update complete",
      "TimePushed": "7/14/2022, 3:03:05 PM"
    },
    {
      "id": "l5kzgqv8z8jix0jcfnm",
      "Status": "git update complete",
      "TimePushed": "7/14/2022, 3:04:09 PM"
    },
    {
      "id": "l5l10awfm2kl3stuc3",
      "Status": "git update complete",
      "TimePushed": "7/14/2022, 3:47:21 PM"
    },
    {
      "id": "l5l11bnhfk9higtm81k",
      "Status": "git update complete",
      "TimePushed": "7/14/2022, 3:48:08 PM"
    },
    {
      "id": "l5l12kmdrqjmdx6j2r",
      "Status": "git update complete",
      "TimePushed": "7/14/2022, 3:49:07 PM"
    },
    {
      "id": "l5l13ti65oi4efyjq06",
      "Status": "git update complete",
      "TimePushed": "7/14/2022, 3:50:05 PM"
    },
    {
      "id": "l5l153qz269bucwtsin",
      "Status": "git update complete",
      "TimePushed": "7/14/2022, 3:51:05 PM"
    },
    {
      "id": "l5l16e0fsyca9u0g56b",
      "Status": "git update complete",
      "TimePushed": "7/14/2022, 3:52:05 PM"
    }
  ]
}